dhtioc/StatsReg.py
dhtioc/__init__.py
dhtioc/_requirements.py
dhtioc/_version.py
dhtioc/datalogger.py
dhtioc/ioc.py
dhtioc/reader.py
dhtioc/trend_analysis.py
dhtioc/utils.py
dhtioc-1.1.1.dist-info/LICENSE
dhtioc-1.1.1.dist-info/METADATA
dhtioc-1.1.1.dist-info/WHEEL
dhtioc-1.1.1.dist-info/entry_points.txt
dhtioc-1.1.1.dist-info/top_level.txt
dhtioc-1.1.1.dist-info/RECORD
